vernemic/__init__.py
vernemic/moby.py
vernemic-1.0.1.dist-info/LICENSE
vernemic-1.0.1.dist-info/METADATA
vernemic-1.0.1.dist-info/WHEEL
vernemic-1.0.1.dist-info/top_level.txt
vernemic-1.0.1.dist-info/RECORD
