Metadata-Version: 2.1
Name: vernemic
Version: 1.0.1
Summary: Mnemonics for ID, eg. Versioning.
Author-email: "Raghav B. Venkataramaiyer" <bvraghav@gmail.com>
Project-URL: Homepage, https://gitlab.com/brutils/vernemic
Project-URL: Docs, https://gitlab.com/brutils/vernemic
Project-URL: Issues, https://gitlab.com/brutils/vernemic/-/issues
Classifier: Programming Language :: Python :: 3
Classifier: License :: OSI Approved :: MIT License
Classifier: Operating System :: OS Independent
License-File: LICENSE
Requires-Dist: pycurl
